{"date_revised": "2026/05/14", "title": "'<i>I can get all the services I want, without fear of being judged</i>': Acceptability of a sexual and reproductive health service for youth in Zimbabwe.", "abstract": "Sexual and reproductive health (SRH) services often do not appeal to youth, leading to limited engagement and poor outcomes. We co-designed a community-based integrated HIV and SRH service with and for youth (16-24 years) in Zimbabwe (CHIEDZA) and investigated its acceptability. Qualitative data from observations of CHIEDZA services (<i>n</i>\u2009=\u200958), and in-depth interviews with healthcare providers (<i>n</i>\u2009=\u200951), mobilisers (<i>n</i>\u2009=\u200923), and clients (<i>n</i>\u2009=\u200963) were analysed inductively and thematically. Participants who attended CHIEDZA in an endline population-based survey completed a questionnaire assessing their experiences. 96.1% of attendees rated their experience as excellent/very good. Four key features were core to CHIEDZA's acceptability. First, in a context where ordinarily '<i>condoms and [menstrual] pads are expensive</i>', and clinics charge user fees, free services at CHIEDZA were valued. Second, integrated SRH services was seen as convenient and increased service uptake: '<i>I came wanting pads, and then also got tested for HIV</i>'. Third, youth-focused '<i>open-minded</i>' interactions with healthcare providers were central to acceptability. Fourth, a social and safe space for youth was popular. The key reasons for non-attendance was not knowing about CHIEDZA and distance. Youth engagement with SRH services could be enhanced by offering free-of-cost, integrated services and supporting healthcare providers to deliver compassionate and youth-focused care.", "doi": "10.1080/17441692.2026.2648360", "authors": ["Constance R S Mackworth-Young", "Constancia Mavodza", "Victoria Simms", "Rangarirayi Nyamwanza", "Portia Nzombe", "Chido Dziva Chikwari", "Mandikudza Tembo", "Tsitsi Bandason", "Ethel Dauya", "Rashida A Ferrand", "Sarah Bernays"], "publication": "Global public health", "pmc_full_text_id": null}